cbgen/_ffi.cpython-310-x86_64-linux-gnu.so
cbgen/example.py
cbgen/samples.c
cbgen/conftest.py
cbgen/__init__.py
cbgen/genotype.c
cbgen/_env.py
cbgen/interface.h
cbgen/partition.h
cbgen/samples.h
cbgen/_ffi.cpython-311-x86_64-linux-musl.so
cbgen/partition.c
cbgen/_ffi.cpython-39-x86_64-linux-gnu.so
cbgen/typing.py
cbgen/_bgen_metafile.py
cbgen/_testit.py
cbgen/_bgen_file.py
cbgen/genotype.h
cbgen/test/__init__.py
cbgen/test/test_bgen.py
cbgen.libs/libncursesw-d80f65ca.so.6.4
cbgen-1.0.6.dist-info/WHEEL
cbgen-1.0.6.dist-info/LICENSE
cbgen-1.0.6.dist-info/RECORD
cbgen-1.0.6.dist-info/METADATA
