Metadata-Version: 2.1
Name: cbgen
Version: 1.0.6
Summary: Python wrapper around a BGEN library
Home-page: https://github.com/limix/cbgen
License: MIT
Keywords: bgen,reader,genetics
Author: Carl Kadie
Author-email: carlk@msn.com
Requires-Python: >=3.9,<4.0
Classifier: License :: OSI Approved :: MIT License
Classifier: Programming Language :: Python :: 3
Classifier: Programming Language :: Python :: 3.9
Classifier: Programming Language :: Python :: 3.10
Classifier: Programming Language :: Python :: 3.11
Classifier: Programming Language :: Python :: 3.12
Requires-Dist: appdirs
Requires-Dist: cffi
Requires-Dist: numpy (>=2.0,<3.0)
Requires-Dist: pooch
Requires-Dist: pytest
Requires-Dist: urllib3 (>=1.26)
Project-URL: Repository, https://github.com/limix/cbgen
